{
  "unpublishedCollection": {
    "name": "Tablefilter",
    "pageId": "Index",
    "pluginId": "js-plugin",
    "pluginType": "JS",
    "actions": [],
    "archivedActions": [],
    "body": "export default {\n\tallPlatforms: GetPlatforms.data.results,\n\tFilter: () => {\t\n\t\tconsole.log(this.allPlatforms);\n\t\tconsole.log('this is a test');\n\t\tconst filtered = this.allPlatforms.filter(platform => platform.name.toLowerCase().includes(Platforms_general.searchText.toLowerCase()));\n\t\tPlatforms_general.tableData = filtered;\n\t\tconsole.log(filtered);\n\t}\n}",
    "variables": [
      {
        "name": "allPlatforms",
        "value": "GetPlatforms.data.results"
      }
    ],
    "userPermissions": []
  },
  "id": "Index_Tablefilter",
  "deleted": false,
  "gitSyncId": "6391e4da1a6c7b62d5cb9236_639730e1038c74195c0a95e7"
}